konnoohmachi-1.0.0.dist-info/METADATA
konnoohmachi-1.0.0.dist-info/WHEEL
konnoohmachi-1.0.0.dist-info/license_files/LICENSE
konnoohmachi/__init__.py
konnoohmachi/konnoohmachi.cpython-37m-darwin.so
konnoohmachi-1.0.0.dist-info/RECORD
