Metadata-Version: 2.1
Name: konnoohmachi
Version: 1.0.0
Classifier: Topic :: Software Development
Requires-Dist: numpy ~= 1.21.0; extra == 'tests'
Requires-Dist: obspy; extra == 'tests'
Requires-Dist: pytest; extra == 'tests'
Provides-Extra: tests
License-File: LICENSE
Summary: Spectral smoothing in Rust/Python
Keywords: seismology,spectral smoothing
Author: Marius Kriegerowski <marius.kriegerowski@gmail.com>
Author-email: Marius Kriegerowski <marius.kriegerowski@gmail.com>
License: MIT
